app/main.py
shithappens/__init__.py
shithappens/card.py
shithappens/create_cards.py
shithappens/sort_situations.py
shithappens/utils.py
shithappens/cli/__init__.py
shithappens/cli/utils.py
shithappens/images/expansion-logo.png
shithappens/style/fonts/__init__.py
shithappens/style/fonts/manage.py
shithappens/style/styles/__init__.py
shithappens/style/styles/registration.py
shithappens-4.0.1.dist-info/LICENSE
shithappens-4.0.1.dist-info/METADATA
shithappens-4.0.1.dist-info/WHEEL
shithappens-4.0.1.dist-info/entry_points.txt
shithappens-4.0.1.dist-info/top_level.txt
shithappens-4.0.1.dist-info/RECORD
