Metadata-Version: 2.1
Name: shithappens
Version: 4.0.1
Summary: Create your own Shit Happens playing cards!
Author: Siem de Jong
License: GNU GENERAL PUBLIC LICENSE
Project-URL: Homepage, https://github.com/siemdejong/shit-happens
Project-URL: Bug Tracker, https://github.com/siemdejong/shit-happens/issues
Keywords: shit happens,card-game
Classifier: Development Status :: 5 - Production/Stable
Classifier: Framework :: Matplotlib
Classifier: Intended Audience :: Developers
Classifier: Intended Audience :: Other Audience
Classifier: License :: OSI Approved :: GNU General Public License v3 (GPLv3)
Classifier: Programming Language :: Python
Classifier: Programming Language :: Python :: 3
Classifier: Programming Language :: Python :: 3 :: Only
Classifier: Programming Language :: Python :: 3.11
Classifier: Topic :: Games/Entertainment :: Board Games
Classifier: Typing :: Typed
Requires-Python: >=3.11
License-File: LICENSE
Requires-Dist: matplotlib
Requires-Dist: pandas
Requires-Dist: openpyxl
Requires-Dist: PyPDF2
Requires-Dist: tqdm
Provides-Extra: dev
Requires-Dist: ruff ; extra == 'dev'
